advermorel/__init__.py
advermorel/advermorel.py
advermorel/losses/__init__.py
advermorel/losses/loat.py
advermorel/losses/mart.py
advermorel/losses/morel.py
advermorel/losses/trades.py
advermorel/models/__init__.py
advermorel/models/main_nets.py
advermorel/models/morelnet.py
advermorel/utils/__init__.py
advermorel/utils/misc.py
advermorel/utils/train_utils.py
advermorel-0.1.6.dist-info/licenses/AUTHORS.rst
advermorel-0.1.6.dist-info/licenses/LICENSE
advermorel-0.1.6.dist-info/METADATA
advermorel-0.1.6.dist-info/WHEEL
advermorel-0.1.6.dist-info/top_level.txt
advermorel-0.1.6.dist-info/RECORD
