Metadata-Version: 2.4
Name: advermorel
Version: 0.1.6
Summary: MOREL is a multi-objective optimization framework for improving DNN robustness against adversarial attacks.
Author-email: Sedjro Salomon Hotegni <salomon.hotegni@tu-dortmund.de>
Maintainer-email: Sedjro Salomon Hotegni <salomon.hotegni@tu-dortmund.de>
License: MIT license
Project-URL: bugs, https://github.com/salomonhotegni/MOREL/issues
Project-URL: changelog, https://github.com/salomonhotegni/MOREL/blob/master/changelog.md
Project-URL: homepage, https://github.com/salomonhotegni/MOREL
License-File: LICENSE
License-File: AUTHORS.rst
Requires-Dist: typer
Requires-Dist: adversarial-robustness-toolbox>=1.19.2
Requires-Dist: datasets>=3.6.0
Requires-Dist: huggingface-hub>=0.33.1
Requires-Dist: numpy>=2.1.2
Requires-Dist: pandas>=2.3.0
Requires-Dist: pillow>=11.0.0
Requires-Dist: scikit-learn>=1.7.0
Requires-Dist: scipy>=1.16.0
Requires-Dist: setuptools>=78.1.1
Requires-Dist: tqdm>=4.67.1
Provides-Extra: dev
Requires-Dist: coverage; extra == "dev"
Requires-Dist: mypy; extra == "dev"
Requires-Dist: pytest; extra == "dev"
Requires-Dist: ruff; extra == "dev"
Dynamic: license-file
